{"t1":"特殊装备","t2":null,"groupId":16,"tips":"血魔流","position":"辅助装备","lv":105,"naijiu":null,"trade":"无法交易","price":24864,"fame":748,"prop":{"base":[{"id":6,"index":null,"label":"力量","num":149,"info":null,"isRate":false},{"id":7,"index":null,"label":"智力","num":149,"info":null,"isRate":false},{"id":8,"index":null,"label":"体力","num":149,"info":null,"isRate":false},{"id":9,"index":null,"label":"精神","num":149,"info":null,"isRate":false}],"effect":[{"id":22,"index":null,"label":"技能攻击力","num":0.12,"info":null,"isRate":true},{"id":-2,"index":null,"label":"","num":null,"info":null,"isRate":false},{"id":-2,"index":null,"label":"该装备的成长属性等级之和达到240，增加1%的技能攻击力","num":null,"info":null,"isRate":false},{"id":-2,"index":null,"label":" - 该装备的成长属性等级之和每增加40级，额外增加1%的技能攻击力","num":null,"info":null,"isRate":false},{"id":-2,"index":null,"label":" - 穿戴100级以下装备时不适用该效果","num":null,"info":null,"isRate":false}],"growthProps":[{"id":994,"fromType":null,"index":1,"buffer":470,"attack":1078,"level":null,"type":null,"propsStr":"角色进入睡眠状态时，在10秒内恢复60%的HP","props":["角色进入睡眠状态时，在10秒内恢复60%的HP"],"propsStr2":"自身处于睡眠状态时，在10秒内恢复60%的HP（冷却时间10秒）","props2":["自身处于睡眠状态时，在10秒内恢复60%的HP（冷却时间10秒）"],"buffer2":470,"attack2":1078},{"id":993,"fromType":null,"index":2,"buffer":470,"attack":1078,"level":null,"type":null,"propsStr":"角色进入睡眠状态时，技能冷却时间恢复速度 +50%(觉醒技能除外)","props":["角色进入睡眠状态时，技能冷却时间恢复速度 +50%(觉醒技能除外)"],"propsStr2":"自身处于睡眠状态时，技能冷却时间恢复速度 +50%，持续10秒（冷却时间10秒，觉醒技能除外）","props2":["自身处于睡眠状态时，技能冷却时间恢复速度 +50%，持续10秒（冷却时间10秒，觉醒技能除外）"],"buffer2":470,"attack2":1078},{"id":11,"fromType":null,"index":3,"buffer":494,"attack":1186,"level":null,"type":null,"propsStr":"回避率 +8%","props":["回避率 +8%"],"propsStr2":"回避率 +8%","props2":["回避率 +8%"],"buffer2":494,"attack2":1186},{"id":1,"fromType":null,"index":4,"buffer":494,"attack":1186,"level":null,"type":null,"propsStr":"HP MAX +600","props":["HP MAX +600"],"propsStr2":"HP MAX +600","props2":["HP MAX +600"],"buffer2":494,"attack2":1186}],"bufferProps":[{"id":101,"index":null,"label":"Buff量","num":1875,"info":null,"isRate":false},{"id":999,"index":null,"label":"Lv30 buff技能Lv+1","num":null,"info":null,"isRate":false},{"id":999,"index":null,"label":"Lv50 主动技能Lv+1","num":null,"info":null,"isRate":false}]},"propTypes":[{"value":1,"parent":0,"label":"HP MAX","children":null},{"value":10,"parent":0,"label":"回避率","children":null},{"value":2,"parent":0,"label":"HP恢复","children":null},{"value":37,"parent":0,"label":"技能冷却时间恢复速度","children":null}],"id":182,"rarity":6,"name":"梦之呼唤","num":709,"nameCN":"梦之呼唤","icon":"/specials/support/321.png","group":null}