{"t1":"防具","t2":"头肩","groupId":17,"tips":"异常增伤","position":"板甲(头肩)","lv":105,"naijiu":48,"trade":"无法交易","price":24864,"fame":748,"prop":{"base":[{"id":4,"index":null,"label":"物理防御力","num":5324,"info":null,"isRate":false},{"id":6,"index":null,"label":"力量","num":141,"info":null,"isRate":false},{"id":7,"index":null,"label":"智力","num":141,"info":null,"isRate":false},{"id":8,"index":null,"label":"体力","num":145,"info":null,"isRate":false},{"id":9,"index":null,"label":"精神","num":100,"info":null,"isRate":false}],"effect":[{"id":22,"index":null,"label":"技能攻击力","num":0.34,"info":null,"isRate":true},{"id":-2,"index":null,"label":"","num":null,"info":null,"isRate":false},{"id":-2,"index":null,"label":"该装备的成长属性等级之和达到240，增加1%的技能攻击力","num":null,"info":null,"isRate":false},{"id":-2,"index":null,"label":" - 该装备的成长属性等级之和每增加40级，额外增加1%的技能攻击力","num":null,"info":null,"isRate":false},{"id":-2,"index":null,"label":" - 穿戴100级以下装备时不适用该效果","num":null,"info":null,"isRate":false}],"growthProps":[{"id":1169,"fromType":null,"index":1,"buffer":466,"attack":943,"level":null,"type":null,"propsStr":"向地图最强敌人生成标志，500px范围内存在标志敌人时，施放后跳，可移动至标志敌人后方(冷却时间20秒)<br>背击标志敌人时，技能攻击力 +8%，效果持续5秒(最多叠加1次)","props":["向地图最强敌人生成标志，500px范围内存在标志敌人时，施放后跳，可移动至标志敌人后方(冷却时间20秒)","背击标志敌人时，技能攻击力 +8%，效果持续5秒(最多叠加1次)"],"propsStr2":"向地图最强敌人生成标志，500px范围内存在标志敌人时，施放后跳，可移动至标志敌人后方(冷却时间20秒)<br>背击标志敌人时，技能攻击力 +8%，效果持续5秒(最多叠加1次)","props2":["向地图最强敌人生成标志，500px范围内存在标志敌人时，施放后跳，可移动至标志敌人后方(冷却时间20秒)","背击标志敌人时，技能攻击力 +8%，效果持续5秒(最多叠加1次)"],"buffer2":466,"attack2":1616},{"id":843,"fromType":null,"index":2,"buffer":466,"attack":943,"level":null,"type":null,"propsStr":"背击攻击时，使敌人随机进入出血、灼伤、中毒、感电状态中的1种，效果持续10秒(冷却时间10秒)<br>所有异常状态抗性 +10%","props":["背击攻击时，使敌人随机进入出血、灼伤、中毒、感电状态中的1种，效果持续10秒(冷却时间10秒)","所有异常状态抗性 +10%"],"propsStr2":"背击攻击时，使敌人随机进入出血、灼伤、中毒、感电状态中的1种，效果持续10秒(冷却时间10秒)<br>所有异常状态抗性 +10%","props2":["背击攻击时，使敌人随机进入出血、灼伤、中毒、感电状态中的1种，效果持续10秒(冷却时间10秒)","所有异常状态抗性 +10%"],"buffer2":466,"attack2":1616},{"id":11,"fromType":null,"index":3,"buffer":494,"attack":1186,"level":null,"type":null,"propsStr":"回避率 +8%","props":["回避率 +8%"],"propsStr2":"回避率 +8%","props2":["回避率 +8%"],"buffer2":494,"attack2":1186},{"id":5,"fromType":null,"index":4,"buffer":494,"attack":1186,"level":null,"type":null,"propsStr":"物理防御力 +7000<br>魔法防御力 +7000","props":["物理防御力 +7000","魔法防御力 +7000"],"propsStr2":"物理防御力 +7000<br>魔法防御力 +7000","props2":["物理防御力 +7000","魔法防御力 +7000"],"buffer2":494,"attack2":1186}],"bufferProps":[{"id":101,"index":null,"label":"Buff量","num":1010,"info":null,"isRate":false},{"id":999,"index":null,"label":"Lv30 buff技能Lv+1","num":null,"info":null,"isRate":false},{"id":999,"index":null,"label":"Lv50 主动技能Lv+1","num":null,"info":null,"isRate":false}]},"propTypes":[{"value":69,"parent":0,"label":"灼伤状态","children":null},{"value":7,"parent":0,"label":"防御力","children":null},{"value":10,"parent":0,"label":"回避率","children":null},{"value":61,"parent":0,"label":"出血状态","children":null},{"value":65,"parent":0,"label":"中毒状态","children":null},{"value":73,"parent":0,"label":"感电状态","children":null},{"value":34,"parent":0,"label":"技能攻击力","children":null},{"value":57,"parent":0,"label":"所有异常状态抗性","children":null}],"id":168,"rarity":6,"name":"玉化亡灵肩甲","num":1803,"nameCN":"玉化亡灵肩甲","icon":"/armors/plate_neck/91.png","group":null}